LICENSE
README.md
README.rst
requirements.txt
setup.cfg
setup.py
bin/msftp
bin/msftp-putty.cmd
bin/msftp.cmd
bin/mssh
bin/mssh-putty.cmd
bin/mssh.cmd
doc/Makefile
doc/README.rst
doc/source/README.rst
doc/source/conf.py
doc/source/index.rst
ec2instanceconnectcli/EC2InstanceConnectCLI.py
ec2instanceconnectcli/EC2InstanceConnectCommand.py
ec2instanceconnectcli/EC2InstanceConnectKey.py
ec2instanceconnectcli/EC2InstanceConnectLogger.py
ec2instanceconnectcli/__init__.py
ec2instanceconnectcli/ec2_util.py
ec2instanceconnectcli/input_parser.py
ec2instanceconnectcli/key_publisher.py
ec2instanceconnectcli/key_utils.py
ec2instanceconnectcli/mops.py
ec2instanceconnectcli/mputty.py
ec2instanceconnectcli/py2py3.py
ec2instanceconnectcli_ptc.egg-info/PKG-INFO
ec2instanceconnectcli_ptc.egg-info/SOURCES.txt
ec2instanceconnectcli_ptc.egg-info/dependency_links.txt
ec2instanceconnectcli_ptc.egg-info/requires.txt
ec2instanceconnectcli_ptc.egg-info/top_level.txt